Flowmaid/__init__.py
flowmaid/__init__.py
flowmaid-0.0.1.dist-info/METADATA
flowmaid-0.0.1.dist-info/WHEEL
flowmaid-0.0.1.dist-info/top_level.txt
flowmaid-0.0.1.dist-info/RECORD
