Metadata-Version: 2.1
Name: flowmaid
Version: 0.0.1
Summary: A pure Python library designed to convert Mermaid flowcharts into SVG.
Home-page: https://github.com/aghasemi/flowmaid.py
Author: Alireza Ghasemi
Author-email: ghasemi.a.ir@gmail.com
Keywords: Python,Mermaid.js
Requires-Python: >=3.8
